sAsync-0.9.3.dist-info/METADATA
sAsync-0.9.3.dist-info/RECORD
sAsync-0.9.3.dist-info/WHEEL
sAsync-0.9.3.dist-info/top_level.txt
sasync/__init__.py
sasync/database.py
sasync/errors.py
sasync/items.py
sasync/parray.py
sasync/queue.py
sasync/selex.py
sasync/test/__init__.py
sasync/test/people.py
sasync/test/test_database.py
sasync/test/test_items.py
sasync/test/test_parray.py
sasync/test/test_queue.py
sasync/test/testbase.py
