Metadata-Version: 2.1
Name: sAsync
Version: 0.9.3
Summary: SQLAlchemy done Asynchronously: Twisted-friendly access to an SQL database.
Home-page: http://edsuom.com/sAsync.html
Author: Edwin A. Suominen
Author-email: foss@edsuom.com
Maintainer: Edwin A. Suominen
Maintainer-email: foss@edsuom.com
License: Apache License (2.0)
Project-URL: API, http://edsuom.com/sAsync/sasync.html
Project-URL: GitHub, https://github.com/edsuom/sAsync
Keywords: SQL,SQLAlchemy,twisted,asynchronous,async,persist,persistence,persistent,database,sqlite,mysql
Platform: OS Independent
Classifier: Development Status :: 5 - Production/Stable
Classifier: Intended Audience :: Developers
Classifier: License :: OSI Approved :: Apache Software License
Classifier: Operating System :: OS Independent
Classifier: Programming Language :: Python :: 2.7
Classifier: Programming Language :: Python :: 2 :: Only
Classifier: Framework :: Twisted
Classifier: Topic :: Database
Classifier: Topic :: Database :: Front-Ends
Classifier: Topic :: Database :: Database Engines/Servers
Classifier: Topic :: Software Development :: Libraries :: Python Modules
Requires-Dist: SQLAlchemy (>=0.5)
Requires-Dist: AsynQueue (>=0.9.4)
